twitch_fapi_backend/__init__.py
twitch_fapi_backend/api.py
twitch_fapi_backend/kodi.py
twitch_fapi_backend/tasks.py
twitch_fapi_backend/twitch.py
twitch_fapi_backend-0.1.0.dist-info/METADATA
twitch_fapi_backend-0.1.0.dist-info/WHEEL
twitch_fapi_backend-0.1.0.dist-info/entry_points.txt
twitch_fapi_backend-0.1.0.dist-info/RECORD
