Metadata-Version: 2.1
Name: twitch_fapi_backend
Version: 0.1.0
Summary: 
Author: david
Author-email: davidventura27@gmail.com
Requires-Python: >=3.11,<4.0
Classifier: Programming Language :: Python :: 3
Classifier: Programming Language :: Python :: 3.11
Classifier: Programming Language :: Python :: 3.12
Requires-Dist: aiocache (>=0.11.1,<0.12.0)
Requires-Dist: aiomqtt (>=1.0.0,<2.0.0)
Requires-Dist: dynaconf (>=3.1.7,<4.0.0)
Requires-Dist: fastapi (>=0.95.1,<0.96.0)
Requires-Dist: httpx (>=0.27.2,<0.28.0)
Requires-Dist: pychromecast (>=13.1.0,<14.0.0)
Requires-Dist: shiv (>=1.0.0,<2.0.0)
Requires-Dist: streamlink (==6.5.1)
Requires-Dist: twitch-dota-extension (>=0.1.10,<0.2.0)
Requires-Dist: ujson (>=5.1.0,<6.0.0)
Requires-Dist: uvicorn (>=0.16.0,<0.17.0)
Requires-Dist: wheel (>=0.37.1,<0.38.0)
